hct/__init__.py
hct/cooling_system.py
hct/fan_data.py
hct/generalplotsettings.py
hct/heat_spreading.py
hct/hydrodynamic.py
hct/optimization.py
hct/thermal_dataclasses.py
hct-0.0.2.dist-info/METADATA
hct-0.0.2.dist-info/WHEEL
hct-0.0.2.dist-info/RECORD
