Metadata-Version: 2.4
Name: hct
Version: 0.0.2
Summary: Heat sink computation toolbox: Calculate and optimize fan cooled heat sink systems for power electronics converters.
Project-URL: Homepage, https://github.com/upb-lea/HCT_heat_sink_computation_toolbox
Project-URL: Issues, https://github.com/upb-lea/HCT_heat_sink_computation_toolbox/issues
Author: LEA
Classifier: License :: OSI Approved :: MIT License
Classifier: Operating System :: OS Independent
Classifier: Programming Language :: Python :: 3
Requires-Python: >=3.10
Requires-Dist: deepdiff
Requires-Dist: matplotlib>=3.8.2
Requires-Dist: numpy>=1.26.4
Requires-Dist: optuna>=3.6.1
Requires-Dist: pandas>=2.2.2
Requires-Dist: plotly
